Workbook

Sheet Contribuyentes
A1: Libro de Ventas (IVA) · Ventas a contribuyentes
A2: Base: Reglamento General de la Ley del IVA, arts. 70 a 72, 76 y 78 (ventas a contribuyentes y no contribuyentes van separadas).
A4: Contribuyente (razón social) | D4: Azullab Farmacia, C.A. | O4: Alícuota general | P4: 0.16
A5: RIF | D5: J-XXXXXXXX-X | O5: Alícuota reducida | P5: 0.08
A6: Período (mes y año) | D6: Octubre 2026
A7: Moneda | D7: Bolívares (Bs). Los libros se llevan en moneda nacional (COT art. 102, num. 8).
A9: Cómo llenarlo | D9: Aquí van una por una las facturas emitidas con RIF del cliente, las notas de débito y las notas de crédito (en negativo). Las ventas a consumidor final por máquina fiscal se anotan en la hoja "Máquina fiscal (Reporte Z)". Escribe solo en azul; las filas grises son ejemplos.
A11: N° Op. | B11: Fecha | C11: Tipo de documento (FAC, ND, NC) | D11: N° del documento | E11: N° de control o serial de máquina fiscal | F11: N° factura afectada (solo ND y NC) | G11: RIF del cliente | H11: Nombre o razón social del cliente | I11: Total ventas incluyendo IVA | J11: Ventas exentas, exoneradas o no sujetas | K11: Base imponible alícuota general | L11: Débito fiscal alícuota general | M11: Base imponible alícuota reducida | N11: Débito fiscal alícuota reducida | O11: IVA retenido por el cliente (si es agente de retención) | P11: N° comprobante de retención | Q11: IGTF percibido (solo si la farmacia es contribuyente especial)
A12: =IF(B12="","",ROW()-11) -> 1 | B12: 46320 | C12: FAC | D12: 00001188 | E12: Z7C0012345 | G12: J-98765432-1 | H12: Unidad Educativa Ejemplo | I12: =IF(B12="","",SUM(J12:N12)) -> 33753.79 | J12: 14286.46 | K12: 16782.18 | L12: =IF(K12="","",ROUND(K12*$P$4,2)) -> 2685.15 | M12: 0 | N12: =IF(M12="","",ROUND(M12*$P$5,2)) -> 0
A13: =IF(B13="","",ROW()-11) -> 2 | B13: 46321 | C13: NC | D13: 00000004 | E13: Z7C0012345 | F13: 00001188 | G13: J-98765432-1 | H13: Unidad Educativa Ejemplo | I13: =IF(B13="","",SUM(J13:N13)) -> -1587.38 | J13: -1587.38 | K13: 0 | L13: =IF(K13="","",ROUND(K13*$P$4,2)) -> 0 | M13: 0 | N13: =IF(M13="","",ROUND(M13*$P$5,2)) -> 0
A14: =IF(B14="","",ROW()-11) | I14: =IF(B14="","",SUM(J14:N14)) | L14: =IF(K14="","",ROUND(K14*$P$4,2)) | N14: =IF(M14="","",ROUND(M14*$P$5,2))
A15: =IF(B15="","",ROW()-11) | I15: =IF(B15="","",SUM(J15:N15)) | L15: =IF(K15="","",ROUND(K15*$P$4,2)) | N15: =IF(M15="","",ROUND(M15*$P$5,2))
A16: =IF(B16="","",ROW()-11) | I16: =IF(B16="","",SUM(J16:N16)) | L16: =IF(K16="","",ROUND(K16*$P$4,2)) | N16: =IF(M16="","",ROUND(M16*$P$5,2))
A17: =IF(B17="","",ROW()-11) | I17: =IF(B17="","",SUM(J17:N17)) | L17: =IF(K17="","",ROUND(K17*$P$4,2)) | N17: =IF(M17="","",ROUND(M17*$P$5,2))
A18: =IF(B18="","",ROW()-11) | I18: =IF(B18="","",SUM(J18:N18)) | L18: =IF(K18="","",ROUND(K18*$P$4,2)) | N18: =IF(M18="","",ROUND(M18*$P$5,2))
A19: =IF(B19="","",ROW()-11) | I19: =IF(B19="","",SUM(J19:N19)) | L19: =IF(K19="","",ROUND(K19*$P$4,2)) | N19: =IF(M19="","",ROUND(M19*$P$5,2))
A20: =IF(B20="","",ROW()-11) | I20: =IF(B20="","",SUM(J20:N20)) | L20: =IF(K20="","",ROUND(K20*$P$4,2)) | N20: =IF(M20="","",ROUND(M20*$P$5,2))
A21: =IF(B21="","",ROW()-11) | I21: =IF(B21="","",SUM(J21:N21)) | L21: =IF(K21="","",ROUND(K21*$P$4,2)) | N21: =IF(M21="","",ROUND(M21*$P$5,2))
A22: =IF(B22="","",ROW()-11) | I22: =IF(B22="","",SUM(J22:N22)) | L22: =IF(K22="","",ROUND(K22*$P$4,2)) | N22: =IF(M22="","",ROUND(M22*$P$5,2))
A23: =IF(B23="","",ROW()-11) | I23: =IF(B23="","",SUM(J23:N23)) | L23: =IF(K23="","",ROUND(K23*$P$4,2)) | N23: =IF(M23="","",ROUND(M23*$P$5,2))
A24: =IF(B24="","",ROW()-11) | I24: =IF(B24="","",SUM(J24:N24)) | L24: =IF(K24="","",ROUND(K24*$P$4,2)) | N24: =IF(M24="","",ROUND(M24*$P$5,2))
A25: =IF(B25="","",ROW()-11) | I25: =IF(B25="","",SUM(J25:N25)) | L25: =IF(K25="","",ROUND(K25*$P$4,2)) | N25: =IF(M25="","",ROUND(M25*$P$5,2))
... A311: =IF(B311="","",ROW()-11) | I311: =IF(B311="","",SUM(J311:N311)) | L311: =IF(K311="","",ROUND(K311*$P$4,2)) | N311: =IF(M311="","",ROUND(M311*$P$5,2))
H312: Totales contribuyentes | I312: =SUM(I12:I311) -> 32166.41 | J312: =SUM(J12:J311) -> 12699.08 | K312: =SUM(K12:K311) -> 16782.18 | L312: =SUM(L12:L311) -> 2685.15 | M312: =SUM(M12:M311) -> 0 | N312: =SUM(N12:N311) -> 0 | O312: =SUM(O12:O311) -> 0 | Q312: =SUM(Q12:Q311) -> 0

Sheet Máquina fiscal (Reporte Z)
A1: Libro de Ventas (IVA) · Resumen diario de máquina fiscal
A2: Base: Reglamento LIVA, art. 77 y su Parágrafo Segundo: el reporte global diario de la máquina fiscal se anota como las ventas a no contribuyentes, con el número de registro de la máquina.
A4: Contribuyente (razón social) | D4: Azullab Farmacia, C.A. | K4: Alícuota general | L4: =Contribuyentes!P4 -> 0.16
A5: RIF | D5: J-XXXXXXXX-X | K5: Alícuota reducida | L5: =Contribuyentes!P5 -> 0.08
A6: Período (mes y año) | D6: Octubre 2026
A7: Moneda | D7: Bolívares (Bs). Los libros se llevan en moneda nacional (COT art. 102, num. 8).
A9: Cómo llenarlo | D9: Una fila por cada Reporte Z (una por día y por máquina). Copia los montos del Reporte Z. Si en el día hubo facturas con RIF que ya anotaste en la hoja "Contribuyentes", resta esos montos aquí para no contarlos dos veces (confírmalo con tu contador). Escribe solo en azul.
A11: N° Op. | B11: Fecha | C11: N° de Reporte Z | D11: Serial (registro) de la máquina fiscal | E11: Primera factura del día | F11: Última factura del día | G11: Total ventas del día incluyendo IVA | H11: Ventas exentas, exoneradas o no sujetas | I11: Base imponible alícuota general | J11: Débito fiscal alícuota general | K11: Base imponible alícuota reducida | L11: Débito fiscal alícuota reducida | M11: IGTF percibido (solo contribuyente especial)
A12: =IF(B12="","",ROW()-11) -> 1 | B12: 46317 | C12: 0083 | D12: Z7C0012345 | E12: 00001101 | F12: 00001131 | G12: =IF(B12="","",SUM(H12:L12)) -> 765022.41 | H12: 591217.36 | I12: 149831.94 | J12: =IF(I12="","",ROUND(I12*$L$4,2)) -> 23973.11 | L12: =IF(K12="","",ROUND(K12*$L$5,2))
A13: =IF(B13="","",ROW()-11) -> 2 | B13: 46318 | C13: 0084 | D13: Z7C0012345 | E13: 00001132 | F13: 00001158 | G13: =IF(B13="","",SUM(H13:L13)) -> 898529.18 | H13: 688012.44 | I13: 181479.95 | J13: =IF(I13="","",ROUND(I13*$L$4,2)) -> 29036.79 | L13: =IF(K13="","",ROUND(K13*$L$5,2)) | M13: 0
A14: =IF(B14="","",ROW()-11) -> 3 | B14: 46319 | C14: 0085 | D14: Z7C0012345 | E14: 00001159 | F14: 00001187 | G14: =IF(B14="","",SUM(H14:L14)) -> 1014652.4 | H14: 784616.31 | I14: 198306.94 | J14: =IF(I14="","",ROUND(I14*$L$4,2)) -> 31729.11 | L14: =IF(K14="","",ROUND(K14*$L$5,2)) | M14: 0
A15: =IF(B15="","",ROW()-11) -> 4 | B15: 46320 | C15: 0086 | D15: Z7C0012345 | E15: 00001189 | F15: 00001248 | G15: =IF(B15="","",SUM(H15:L15)) -> 907055.9 | H15: 702152.85 | I15: 176640.56 | J15: =IF(I15="","",ROUND(I15*$L$4,2)) -> 28262.49 | L15: =IF(K15="","",ROUND(K15*$L$5,2)) | M15: 0
A16: =IF(B16="","",ROW()-11) | G16: =IF(B16="","",SUM(H16:L16)) | J16: =IF(I16="","",ROUND(I16*$L$4,2)) | L16: =IF(K16="","",ROUND(K16*$L$5,2))
A17: =IF(B17="","",ROW()-11) | G17: =IF(B17="","",SUM(H17:L17)) | J17: =IF(I17="","",ROUND(I17*$L$4,2)) | L17: =IF(K17="","",ROUND(K17*$L$5,2))
A18: =IF(B18="","",ROW()-11) | G18: =IF(B18="","",SUM(H18:L18)) | J18: =IF(I18="","",ROUND(I18*$L$4,2)) | L18: =IF(K18="","",ROUND(K18*$L$5,2))
A19: =IF(B19="","",ROW()-11) | G19: =IF(B19="","",SUM(H19:L19)) | J19: =IF(I19="","",ROUND(I19*$L$4,2)) | L19: =IF(K19="","",ROUND(K19*$L$5,2))
A20: =IF(B20="","",ROW()-11) | G20: =IF(B20="","",SUM(H20:L20)) | J20: =IF(I20="","",ROUND(I20*$L$4,2)) | L20: =IF(K20="","",ROUND(K20*$L$5,2))
A21: =IF(B21="","",ROW()-11) | G21: =IF(B21="","",SUM(H21:L21)) | J21: =IF(I21="","",ROUND(I21*$L$4,2)) | L21: =IF(K21="","",ROUND(K21*$L$5,2))
A22: =IF(B22="","",ROW()-11) | G22: =IF(B22="","",SUM(H22:L22)) | J22: =IF(I22="","",ROUND(I22*$L$4,2)) | L22: =IF(K22="","",ROUND(K22*$L$5,2))
A23: =IF(B23="","",ROW()-11) | G23: =IF(B23="","",SUM(H23:L23)) | J23: =IF(I23="","",ROUND(I23*$L$4,2)) | L23: =IF(K23="","",ROUND(K23*$L$5,2))
A24: =IF(B24="","",ROW()-11) | G24: =IF(B24="","",SUM(H24:L24)) | J24: =IF(I24="","",ROUND(I24*$L$4,2)) | L24: =IF(K24="","",ROUND(K24*$L$5,2))
A25: =IF(B25="","",ROW()-11) | G25: =IF(B25="","",SUM(H25:L25)) | J25: =IF(I25="","",ROUND(I25*$L$4,2)) | L25: =IF(K25="","",ROUND(K25*$L$5,2))
A26: =IF(B26="","",ROW()-11) | G26: =IF(B26="","",SUM(H26:L26)) | J26: =IF(I26="","",ROUND(I26*$L$4,2)) | L26: =IF(K26="","",ROUND(K26*$L$5,2))
A27: =IF(B27="","",ROW()-11) | G27: =IF(B27="","",SUM(H27:L27)) | J27: =IF(I27="","",ROUND(I27*$L$4,2)) | L27: =IF(K27="","",ROUND(K27*$L$5,2))
... A73: =IF(B73="","",ROW()-11) | G73: =IF(B73="","",SUM(H73:L73)) | J73: =IF(I73="","",ROUND(I73*$L$4,2)) | L73: =IF(K73="","",ROUND(K73*$L$5,2))
F74: Totales máquina fiscal | G74: =SUM(G12:G73) -> 3585259.9 | H74: =SUM(H12:H73) -> 2765999 | I74: =SUM(I12:I73) -> 706259.39 | J74: =SUM(J12:J73) -> 113001.5 | K74: =SUM(K12:K73) -> 0 | L74: =SUM(L12:L73) -> 0 | M74: =SUM(M12:M73) -> 0

Sheet Resumen del período
A1: Libro de Ventas · Resumen del período (art. 72)
A2: Debe coincidir con la declaración mensual de IVA (forma 30). Todo se calcula solo; no escribas aquí.
A4: Concepto | B4: Contribuyentes | C4: Máquina fiscal | D4: Total
A5: Ventas exentas, exoneradas o no sujetas | B5: =Contribuyentes!J312 -> 12699.08 | C5: ='Máquina fiscal (Reporte Z)'!H74 -> 2765999 | D5: =B5+C5 -> 2778698
A6: Base imponible alícuota general | B6: =Contribuyentes!K312 -> 16782.18 | C6: ='Máquina fiscal (Reporte Z)'!I74 -> 706259.39 | D6: =B6+C6 -> 723041.57
A7: Débito fiscal alícuota general | B7: =Contribuyentes!L312 -> 2685.15 | C7: ='Máquina fiscal (Reporte Z)'!J74 -> 113001.5 | D7: =B7+C7 -> 115686.65
A8: Base imponible alícuota reducida | B8: =Contribuyentes!M312 -> 0 | C8: ='Máquina fiscal (Reporte Z)'!K74 -> 0 | D8: =B8+C8 -> 0
A9: Débito fiscal alícuota reducida | B9: =Contribuyentes!N312 -> 0 | C9: ='Máquina fiscal (Reporte Z)'!L74 -> 0 | D9: =B9+C9 -> 0
A10: Total ventas incluyendo IVA | B10: =Contribuyentes!I312 -> 32166.41 | C10: ='Máquina fiscal (Reporte Z)'!G74 -> 3585259.9 | D10: =B10+C10 -> 3617426.3
A11: IVA retenido por clientes (comprobantes recibidos) | B11: =Contribuyentes!O312 -> 0 | C11: 0 | D11: =B11+C11 -> 0
A12: IGTF percibido (solo contribuyente especial) | B12: =Contribuyentes!Q312 -> 0 | C12: ='Máquina fiscal (Reporte Z)'!M74 -> 0 | D12: =B12+C12 -> 0
A14: Débito fiscal total del período | D14: =D7+D9 -> 115686.65
